pelican/plugins/references/__init__.py
pelican/plugins/references/labels/__init__.py
pelican/plugins/references/labels/number_brackets.py
pelican/plugins/references/references.py
pelican/plugins/references/settings.py
pelican/plugins/references/test_references.py
pelican_references-0.3.1.dist-info/METADATA
pelican_references-0.3.1.dist-info/WHEEL
pelican_references-0.3.1.dist-info/entry_points.txt
pelican_references-0.3.1.dist-info/RECORD
